{"resourceType":"Practitioner","id":"practitioner-alice-yin","text":{"status":"generated","div":"<div xmlns=\"http://www.w3.org/1999/xhtml\"><p><b>Generated Narrative</b></p><p><b>active</b>: true</p><p><b>name</b>: ALICE YIN </p><p><b>telecom</b>: ph: 555-555-8818(HOME)</p><p><b>address</b>: 1235 Bay Ave. Boston MA 02101 US </p><p><b>gender</b>: female</p><p><b>birthDate</b>: 1972-09-04</p></div>"},"active":true,"name":[{"family":"YIN","given":["ALICE"]}],"telecom":[{"system":"phone","value":"555-555-8818","use":"home"}],"address":[{"line":["1235 Bay Ave."],"city":"Boston","state":"MA","postalCode":"02101","country":"US"}],"gender":"female","birthDate":"1972-09-04"}